{
  "version": "1.2.0",
  "updated": "2026-03-05",
  "modules": [
    {
      "slug": "comments",
      "name": "Reacties",
      "description": "Laat bezoekers reacties plaatsen op pagina's en nieuwsberichten. Met moderatie, spambeveiliging en een inbox in het admin paneel.",
      "version": "1.0.2",
      "author": "ROICT",
      "category": "Community",
      "icon": "chat-dots",
      "tags": [
        "comments",
        "reacties",
        "community",
        "bezoekers"
      ],
      "downloads": 0,
      "rating": 5.0,
      "price": "free",
      "download_url": "https://github.com/rorymeijer/roictcms_modules/raw/main/comments.zip"
    },
    {
      "slug": "site-statistics",
      "name": "Site statistieken",
      "description": "Bekijk de statistieken zoals bezoekersaantallen van je website.",
      "version": "1.0.1",
      "author": "ROICT",
      "category": "Statistics",
      "icon": "world",
      "tags": [
        "statistieken",
        "bezoekers",
        "analytics"
      ],
      "downloads": 0,
      "rating": 5.0,
      "price": "free",
      "download_url": "https://github.com/rorymeijer/roictcms_modules/raw/main/site-statistics.zip"
    },
    {
      "slug": "wysiwyg-editor",
      "name": "WYSIWYG Editor",
      "description": "Voegt een visuele rich-text editor toe aan alle content-tekstvakken in het admin paneel. Gebaseerd op Quill.js (open source, MIT). De afbeeldingsknop opent de interne media manager in plaats van een upload-dialoog.",
      "version": "1.1.3",
      "author": "ROICT",
      "category": "Editor",
      "icon": "pencil-square",
      "tags": [
        "editor",
        "wysiwyg",
        "rich-text",
        "content"
      ],
      "downloads": 0,
      "rating": 5.0,
      "price": "free",
      "download_url": "https://github.com/rorymeijer/roictcms_modules/raw/main/wysiwyg-editor.zip"
    },
    {
      "slug": "contact-form",
      "name": "Contact Form",
      "description": "Volledig contactformulier met spambeveiliging, e-mailnotificaties en inbox in het admin paneel.",
      "version": "1.0.3",
      "author": "ROICT",
      "category": "Forms",
      "icon": "envelope",
      "tags": [
        "contact",
        "form",
        "email"
      ],
      "downloads": 0,
      "rating": 5.0,
      "price": "free",
      "download_url": "https://github.com/rorymeijer/roictcms_modules/raw/main/contact-form.zip"
    },
    {
      "slug": "two-factor-auth",
      "name": "Two-Factor Authentication",
      "description": "Beveilig beheeraccounts met twee-factor authenticatie (TOTP/RFC 6238). Werkt met Google Authenticator, Microsoft Authenticator en andere TOTP-apps.",
      "version": "1.0.1",
      "author": "ROICT",
      "category": "Security",
      "icon": "shield-lock",
      "tags": [
        "security",
        "2fa",
        "totp",
        "authentication"
      ],
      "downloads": 0,
      "rating": 5.0,
      "price": "free",
      "download_url": "https://github.com/rorymeijer/roictcms_modules/raw/main/two-factor-auth.zip"
    },
    {
      "slug": "role-permission",
      "name": "Role & Permission",
      "description": "Uitgebreid rollen- en rechtenbeheer. Maak eigen rollen aan, wijs rechten toe en koppel gebruikers aan rollen om nauwkeurig te bepalen wie wat mag doen in het beheerpaneel.",
      "version": "1.0.2",
      "author": "ROICT",
      "category": "Security",
      "icon": "shield-check",
      "tags": [
        "roles",
        "permissions",
        "access-control",
        "security",
        "users"
      ],
      "downloads": 0,
      "rating": 5.0,
      "price": "free",
      "download_url": "https://github.com/rorymeijer/roictcms_modules/raw/main/role-permission.zip"
    },
    {
      "slug": "seo-tools",
      "name": "SEO Tools",
      "description": "Beheer SEO-metatags per pagina, genereer automatisch een sitemap.xml en pas robots.txt aan vanuit het beheerpaneel.",
      "version": "1.0.0",
      "author": "ROICT",
      "category": "SEO",
      "icon": "search",
      "tags": [
        "seo",
        "meta",
        "sitemap",
        "google"
      ],
      "downloads": 0,
      "rating": 5.0,
      "price": "free",
      "download_url": "https://github.com/rorymeijer/roictcms_modules/raw/main/seo-tools.zip"
    },
    {
      "slug": "image-gallery",
      "name": "Image Gallery",
      "description": "Maak fotogalerijen en albums aan. Upload afbeeldingen, voeg bijschriften toe en toon ze op de frontend met een ingebouwde lightbox.",
      "version": "1.0.1",
      "author": "ROICT",
      "category": "Media",
      "icon": "images",
      "tags": [
        "gallery",
        "afbeeldingen",
        "album",
        "media",
        "lightbox"
      ],
      "downloads": 0,
      "rating": 5.0,
      "price": "free",
      "download_url": "https://github.com/rorymeijer/roictcms_modules/raw/main/image-gallery.zip"
    },
    {
      "slug": "newsletter",
      "name": "Newsletter",
      "description": "Beheer nieuwsbriefabonnementen. Bezoekers kunnen zich inschrijven, abonnees worden opgeslagen en vanuit het admin paneel kunt u e-mails versturen.",
      "version": "1.0.7",
      "author": "ROICT",
      "category": "Communication",
      "icon": "mailbox",
      "tags": [
        "newsletter",
        "email",
        "abonnees",
        "mailing"
      ],
      "downloads": 0,
      "rating": 5.0,
      "price": "free",
      "download_url": "https://github.com/rorymeijer/roictcms_modules/raw/main/newsletter.zip"
    },
    {
      "slug": "backup-manager",
      "name": "Backup Manager",
      "description": "Maak databaseback-ups (SQL-dumps), download ze en verwijder verouderde back-ups automatisch. Configuurbaar maximum.",
      "version": "1.0.1",
      "author": "ROICT",
      "category": "Maintenance",
      "icon": "database-down",
      "tags": [
        "backup",
        "database",
        "restore",
        "onderhoud"
      ],
      "downloads": 0,
      "rating": 5.0,
      "price": "free",
      "download_url": "https://github.com/rorymeijer/roictcms_modules/raw/main/backup-manager.zip"
    },
    {
      "slug": "faq",
      "name": "FAQ",
      "description": "Maak en beheer veelgestelde vragen met categorieën. Toon een Bootstrap accordion-widget op de frontend via een PHP-helper.",
      "version": "1.1.2",
      "author": "ROICT",
      "category": "Content",
      "icon": "question-circle",
      "tags": [
        "faq",
        "vragen",
        "accordion",
        "content"
      ],
      "downloads": 0,
      "rating": 5.0,
      "price": "free",
      "download_url": "https://github.com/rorymeijer/roictcms_modules/raw/main/faq.zip"
    },
    {
      "slug": "redirect-manager",
      "name": "Redirect Manager",
      "description": "Beheer 301- en 302-omleidingen. Voeg redirects toe, zet ze aan of uit en bekijk het aantal hits per redirect.",
      "version": "1.0.1",
      "author": "ROICT",
      "category": "SEO",
      "icon": "arrow-left-right",
      "tags": [
        "redirect",
        "301",
        "302",
        "seo",
        "url"
      ],
      "downloads": 0,
      "rating": 5.0,
      "price": "free",
      "download_url": "https://github.com/rorymeijer/roictcms_modules/raw/main/redirect-manager.zip"
    },
    {
      "slug": "frontend-login",
      "name": "Frontend Login",
      "description": "Laat bezoekers inloggen op de frontend. Bescherm pagina's en nieuwsberichten zodat alleen ingelogde leden ze kunnen bekijken. Inclusief registratie, gebruikersbeheer en eenvoudig paginabeheer.",
      "version": "1.0.0",
      "author": "ROICT",
      "category": "Security",
      "icon": "person-lock",
      "tags": [
        "login",
        "leden",
        "beveiliging",
        "afschermen",
        "registratie",
        "frontend"
      ],
      "downloads": 0,
      "rating": 5.0,
      "price": "free",
      "download_url": "https://github.com/rorymeijer/roictcms_modules/raw/main/frontend-login.zip"
    },
    {
      "slug": "slider",
      "name": "Slider / Carousel",
      "description": "Maak en beheer een afbeeldingenslider met tekst, knoppen en links. Toon via shortcode [slider] of PHP-helper op de frontend.",
      "version": "0.0.2",
      "author": "ROICT",
      "category": "Content",
      "icon": "images",
      "tags": [
        "slider",
        "carousel",
        "afbeeldingen",
        "hero"
      ],
      "downloads": 0,
      "rating": 5.0,
      "price": "free",
      "download_url": "https://github.com/rorymeijer/roictcms_modules/raw/main/slider.zip"
    },
    {
      "slug": "video-gallery",
      "name": "Video Gallery",
      "description": "Beheer YouTube en Vimeo video's in galerijen. Detecteert automatisch het platform en maakt embed-links. Toon via shortcode [video_gallery].",
      "version": "0.0.2",
      "author": "ROICT",
      "category": "Media",
      "icon": "play-btn",
      "tags": [
        "video",
        "youtube",
        "vimeo",
        "gallery",
        "media"
      ],
      "downloads": 0,
      "rating": 5.0,
      "price": "free",
      "download_url": "https://github.com/rorymeijer/roictcms_modules/raw/main/video-gallery.zip"
    },
    {
      "slug": "file-library",
      "name": "Bestandsbibliotheek",
      "description": "Upload en beheer bestanden (PDF, documenten). Bezoekers kunnen bestanden downloaden. Downloadteller ingebouwd. Toon via shortcode [file_library].",
      "version": "0.0.2",
      "author": "ROICT",
      "category": "Content",
      "icon": "file-earmark-arrow-down",
      "tags": [
        "bestanden",
        "pdf",
        "download",
        "documenten"
      ],
      "downloads": 0,
      "rating": 5.0,
      "price": "free",
      "download_url": "https://github.com/rorymeijer/roictcms_modules/raw/main/file-library.zip"
    },
    {
      "slug": "testimonials",
      "name": "Testimonials",
      "description": "Beheer klantervaringen en recensies met sterrenwaardering. Toon via shortcode [testimonials] als kaartenoverzicht op de frontend.",
      "version": "0.0.2",
      "author": "ROICT",
      "category": "Content",
      "icon": "chat-quote",
      "tags": [
        "testimonials",
        "recensies",
        "klanten",
        "reviews"
      ],
      "downloads": 0,
      "rating": 5.0,
      "price": "free",
      "download_url": "https://github.com/rorymeijer/roictcms_modules/raw/main/testimonials.zip"
    },
    {
      "slug": "portfolio",
      "name": "Portfolio",
      "description": "Toon projecten en cases met filterfunctie op categorie. Beheer categorieën en items in het admin paneel. Toon via shortcode [portfolio].",
      "version": "0.0.2",
      "author": "ROICT",
      "category": "Content",
      "icon": "grid",
      "tags": [
        "portfolio",
        "projecten",
        "cases",
        "werk"
      ],
      "downloads": 0,
      "rating": 5.0,
      "price": "free",
      "download_url": "https://github.com/rorymeijer/roictcms_modules/raw/main/portfolio.zip"
    },
    {
      "slug": "team",
      "name": "Team",
      "description": "Beheer teamleden met naam, functietitel, bio en foto. Toon via shortcode [team] als responsief kaartenoverzicht op de frontend.",
      "version": "0.0.2",
      "author": "ROICT",
      "category": "Content",
      "icon": "people",
      "tags": [
        "team",
        "medewerkers",
        "over-ons",
        "personeel"
      ],
      "downloads": 0,
      "rating": 5.0,
      "price": "free",
      "download_url": "https://github.com/rorymeijer/roictcms_modules/raw/main/team.zip"
    },
    {
      "slug": "events",
      "name": "Evenementen",
      "description": "Maak en beheer evenementen met datum, tijd, locatie en beschrijving. Toont automatisch toekomstige evenementen. Toon via shortcode [events].",
      "version": "0.0.2",
      "author": "ROICT",
      "category": "Content",
      "icon": "calendar-event",
      "tags": [
        "evenementen",
        "agenda",
        "calendar",
        "events"
      ],
      "downloads": 0,
      "rating": 5.0,
      "price": "free",
      "download_url": "https://github.com/rorymeijer/roictcms_modules/raw/main/events.zip"
    },
    {
      "slug": "vacancies",
      "name": "Vacatures",
      "description": "Beheer vacatures met functieprofiel en eisen. Bezoekers kunnen direct solliciteren via een ingebouwd formulier. Toon via shortcode [vacancies].",
      "version": "0.0.2",
      "author": "ROICT",
      "category": "Content",
      "icon": "briefcase",
      "tags": [
        "vacatures",
        "sollicitaties",
        "werk",
        "hr"
      ],
      "downloads": 0,
      "rating": 5.0,
      "price": "free",
      "download_url": "https://github.com/rorymeijer/roictcms_modules/raw/main/vacancies.zip"
    },
    {
      "slug": "reservations",
      "name": "Reserveringen",
      "description": "Eenvoudig boekingssysteem met tijdslots. Bezoekers reserveren een beschikbaar slot, beheerders zien en beheren alle reserveringen. Toon via shortcode [reservation_form].",
      "version": "0.0.2",
      "author": "ROICT",
      "category": "Content",
      "icon": "calendar-check",
      "tags": [
        "reserveringen",
        "boeken",
        "tijdslots",
        "afspraken"
      ],
      "downloads": 0,
      "rating": 5.0,
      "price": "free",
      "download_url": "https://github.com/rorymeijer/roictcms_modules/raw/main/reservations.zip"
    },
    {
      "slug": "cookie-consent",
      "name": "Cookie Consent",
      "description": "AVG/GDPR-compliant cookiebanner met instelbare teksten en opslag van gebruikersvoorkeur. 'Alles accepteren' of 'Alleen noodzakelijk'.",
      "version": "0.0.2",
      "author": "ROICT",
      "category": "Privacy",
      "icon": "shield-check",
      "tags": [
        "cookie",
        "gdpr",
        "avg",
        "privacy",
        "consent"
      ],
      "downloads": 0,
      "rating": 5.0,
      "price": "free",
      "download_url": "https://github.com/rorymeijer/roictcms_modules/raw/main/cookie-consent.zip"
    },
    {
      "slug": "poll",
      "name": "Enquête / Poll",
      "description": "Maak polls en enkelvoudige enquêtes. Bezoekers stemmen eenmalig (IP-gebaseerd) en zien direct de resultaten als staafdiagram. Toon via shortcode [poll id=\"1\"].",
      "version": "0.0.2",
      "author": "ROICT",
      "category": "Community",
      "icon": "bar-chart",
      "tags": [
        "poll",
        "enquête",
        "stemmen",
        "community"
      ],
      "downloads": 0,
      "rating": 5.0,
      "price": "free",
      "download_url": "https://github.com/rorymeijer/roictcms_modules/raw/main/poll.zip"
    },
    {
      "slug": "price-list",
      "name": "Prijslijst",
      "description": "Maak en beheer prijslijsten en tarieven per categorie. Toon via shortcode [price_list] of gefilterd per categorie [price_list category=\"diensten\"].",
      "version": "0.0.2",
      "author": "ROICT",
      "category": "Content",
      "icon": "tag",
      "tags": [
        "prijslijst",
        "tarieven",
        "diensten",
        "prijs"
      ],
      "downloads": 0,
      "rating": 5.0,
      "price": "free",
      "download_url": "https://github.com/rorymeijer/roictcms_modules/raw/main/price-list.zip"
    },
    {
      "slug": "google-maps",
      "name": "Google Maps",
      "description": "Voeg Google Maps kaarten in op je pagina's via shortcode [google_map id=\"1\"]. Configureer meerdere locaties met adres en zoomniveau.",
      "version": "0.0.2",
      "author": "ROICT",
      "category": "Integratie",
      "icon": "geo-alt",
      "tags": [
        "google-maps",
        "kaart",
        "locatie",
        "maps"
      ],
      "downloads": 0,
      "rating": 5.0,
      "price": "free",
      "download_url": "https://github.com/rorymeijer/roictcms_modules/raw/main/google-maps.zip"
    },
    {
      "slug": "social-feed",
      "name": "Social Feed",
      "description": "Beheer en toon een social media feed met handmatig toegevoegde posts van Instagram, X, Facebook en LinkedIn. Toon via shortcode [social_feed].",
      "version": "0.0.2",
      "author": "ROICT",
      "category": "Social",
      "icon": "rss",
      "tags": [
        "social",
        "feed",
        "instagram",
        "twitter",
        "facebook"
      ],
      "downloads": 0,
      "rating": 5.0,
      "price": "free",
      "download_url": "https://github.com/rorymeijer/roictcms_modules/raw/main/social-feed.zip"
    },
    {
      "slug": "rss-importer",
      "name": "RSS Importer",
      "description": "Importeer externe RSS-feeds en toon als nieuwsoverzicht op de frontend. Ingebouwde cache voor snelle laadtijden. Toon via shortcode [rss_feed id=\"1\"].",
      "version": "0.0.2",
      "author": "ROICT",
      "category": "Integratie",
      "icon": "rss-fill",
      "tags": [
        "rss",
        "feed",
        "nieuws",
        "import",
        "extern"
      ],
      "downloads": 0,
      "rating": 5.0,
      "price": "free",
      "download_url": "https://github.com/rorymeijer/roictcms_modules/raw/main/rss-importer.zip"
    },
    {
      "slug": "webhook-manager",
      "name": "Webhook Manager",
      "description": "Configureer uitgaande webhooks voor CMS-events (nieuw bericht, nieuwe gebruiker etc.). Met HMAC-SHA256 beveiliging en activiteitenlog.",
      "version": "0.0.2",
      "author": "ROICT",
      "category": "Developer",
      "icon": "broadcast",
      "tags": [
        "webhook",
        "integratie",
        "api",
        "developer",
        "events"
      ],
      "downloads": 0,
      "rating": 5.0,
      "price": "free",
      "download_url": "https://github.com/rorymeijer/roictcms_modules/raw/main/webhook-manager.zip"
    },
    {
      "slug": "popup-manager",
      "name": "Popup Manager",
      "description": "Maak en beheer popups op basis van tijd of exit-intent. Ideaal voor aanbiedingen en nieuwsbriefinschrijvingen. Cookie-gebaseerde herhaalcontrole.",
      "version": "0.0.2",
      "author": "ROICT",
      "category": "Marketing",
      "icon": "window-stack",
      "tags": [
        "popup",
        "marketing",
        "conversie",
        "aanbiedingen"
      ],
      "downloads": 0,
      "rating": 5.0,
      "price": "free",
      "download_url": "https://github.com/rorymeijer/roictcms_modules/raw/main/popup-manager.zip"
    },
    {
      "slug": "audit-log",
      "name": "Auditlog",
      "description": "Registreer automatisch alle beheersacties: wie, wat en wanneer. Raadpleeg het activiteitenlogboek in het admin paneel met filtering en automatisch opschonen.",
      "version": "0.0.2",
      "author": "ROICT",
      "category": "Beheer",
      "icon": "clock-history",
      "tags": [
        "audit",
        "log",
        "activiteit",
        "beheer",
        "geschiedenis"
      ],
      "downloads": 0,
      "rating": 5.0,
      "price": "free",
      "download_url": "https://github.com/rorymeijer/roictcms_modules/raw/main/audit-log.zip"
    },
    {
      "slug": "search",
      "name": "Zoekmodule",
      "description": "Voegt zoekfunctionaliteit toe aan de frontend. Zoekt door pagina's en nieuwsberichten. Toon het zoekformulier via shortcode [search_form] en resultaten via [search_results].",
      "version": "0.0.2",
      "author": "ROICT",
      "category": "Content",
      "icon": "search",
      "tags": [
        "zoeken",
        "search",
        "content",
        "frontend"
      ],
      "downloads": 0,
      "rating": 5.0,
      "price": "free",
      "download_url": "https://github.com/rorymeijer/roictcms_modules/raw/main/search.zip"
    },
    {
      "slug": "multilingual",
      "name": "Meertaligheid",
      "description": "Voeg meerdere talen toe aan je website. Beheer vertalingen van pagina's en nieuwsberichten per taal met een instelbare taalwisselaar.",
      "version": "0.0.2",
      "author": "ROICT",
      "category": "Content",
      "icon": "translate",
      "tags": [
        "talen",
        "vertaling",
        "meertalig",
        "i18n",
        "internationaal"
      ],
      "downloads": 0,
      "rating": 5.0,
      "price": "free",
      "download_url": "https://github.com/rorymeijer/roictcms_modules/raw/main/multilingual.zip"
    },
    {
      "slug": "import-export",
      "name": "Import / Export",
      "description": "Exporteer pagina's, nieuws en gebruikers als CSV-bestand. Importeer content via CSV. Bestaande slugs worden automatisch overgeslagen.",
      "version": "0.0.2",
      "author": "ROICT",
      "category": "Beheer",
      "icon": "arrow-down-up",
      "tags": [
        "import",
        "export",
        "csv",
        "migratie",
        "data"
      ],
      "downloads": 0,
      "rating": 5.0,
      "price": "free",
      "download_url": "https://github.com/rorymeijer/roictcms_modules/raw/main/import-export.zip"
    },
    {
      "slug": "cache-manager",
      "name": "Cache Manager",
      "description": "Cach de frontend uitvoer van pagina's voor snellere laadtijden. Configureerbare TTL en uitgesloten URL's. Leeg de cache met één klik.",
      "version": "0.0.2",
      "author": "ROICT",
      "category": "Beheer",
      "icon": "lightning",
      "tags": [
        "cache",
        "performance",
        "snelheid",
        "optimalisatie"
      ],
      "downloads": 0,
      "rating": 5.0,
      "price": "free",
      "download_url": "https://github.com/rorymeijer/roictcms_modules/raw/main/cache-manager.zip"
    },
    {
      "slug": "rest-api",
      "name": "REST API",
      "description": "Publieke JSON REST API endpoints voor pagina's en nieuws. Beveiligd met API keys. Inclusief API-documentatie en key-beheer in het admin paneel.",
      "version": "0.0.2",
      "author": "ROICT",
      "category": "Developer",
      "icon": "code-slash",
      "tags": [
        "api",
        "rest",
        "json",
        "developer",
        "integratie"
      ],
      "downloads": 0,
      "rating": 5.0,
      "price": "free",
      "download_url": "https://github.com/rorymeijer/roictcms_modules/raw/main/rest-api.zip"
    },
    {
      "slug": "maintenance-page",
      "name": "Onderhoudspagina",
      "description": "Toon een volledig instelbare onderhoudspagina aan bezoekers. Beheerders zien de echte site. Configureerbare kleuren, titel en tekst.",
      "version": "0.0.2",
      "author": "ROICT",
      "category": "Beheer",
      "icon": "tools",
      "tags": [
        "onderhoud",
        "maintenance",
        "coming-soon",
        "beheer"
      ],
      "downloads": 0,
      "rating": 5.0,
      "price": "free",
      "download_url": "https://github.com/rorymeijer/roictcms_modules/raw/main/maintenance-page.zip"
    }
  ],
  "themes": []
}
